MANIFEST.in
README.md
setup.cfg
setup.py
examples/__init__.py
examples/bench_label.py
examples/bench_plot.py
tests/__init__.py
tests/base/test_launcher.py
tests/cli/test_utils.py
tests/qt/test_plot.py
widgetmark/__init__.py
widgetmark.egg-info/PKG-INFO
widgetmark.egg-info/SOURCES.txt
widgetmark.egg-info/dependency_links.txt
widgetmark.egg-info/entry_points.txt
widgetmark.egg-info/requires.txt
widgetmark.egg-info/top_level.txt
widgetmark/base/__init__.py
widgetmark/base/benchmark.py
widgetmark/base/executor.py
widgetmark/base/launcher.py
widgetmark/cli/__init__.py
widgetmark/cli/__main__.py
widgetmark/cli/cli.py
widgetmark/cli/cli_view.py
widgetmark/cli/loader.py
widgetmark/qt/__init__.py
widgetmark/qt/benchmark.py
widgetmark/qt/executor.py
widgetmark/qt/plot.py
widgetmark/qt/util.py