Metadata-Version: 2.1
Name: widgetmark
Version: 0.1.0
Summary: Benchmarking Framework for Qt Widgets.
Home-page: https://github.com/fabianSorn/widgetmark
Author: Fabian Sorn
Author-email: fabian.sorn@icloud.com
License: UNKNOWN
Download-URL: https://github.com/fabianSorn/widgetmark/archive/v0.1.tar.gz
Platform: UNKNOWN
Classifier: Programming Language :: Python :: 3
Classifier: Operating System :: OS Independent
Requires-Python: >=3.6, <4
Provides-Extra: testing
Provides-Extra: dev
Provides-Extra: release
Provides-Extra: core
Provides-Extra: all
Provides-Extra: linting
Provides-Extra: doc
